IrcConnector_Edog0049a/IrcConnector.py
IrcConnector_Edog0049a/IrcConnector.pyi
IrcConnector_Edog0049a/TokenBucket.py
IrcConnector_Edog0049a/TokenBucket.pyi
IrcConnector_Edog0049a/__init__.py
IrcConnector_Edog0049a/__init__.pyi
IrcConnector_Edog0049a/utils.py
IrcConnector_Edog0049a/utils.pyi
ircconnector_edog0049a-0.1.0.dist-info/METADATA
ircconnector_edog0049a-0.1.0.dist-info/WHEEL
ircconnector_edog0049a-0.1.0.dist-info/RECORD
